[
 {
	"id": 2,
	"name": "Cake",
	 "category": "Birthday",
	"image": "BirthdayCard1",
	 "page2": "HA1",
	 "price": 4.00,
	 "hairPlacex": 0.00,
    	"hairPlacey": 0.00,
	"eyePlacex": -45.00,
    	"eyePlacey": 150.00,
	"caption": "HIP HIP Hello"
 },
 {
	"id": 3,
	"name": "Golf",
	 "category": "Birthday",
	"image": "Golf Draft 1",
	 "page2": "HA1",
	 "price": 4.00,
	 "hairPlacex": 0.00,
    	"hairPlacey": 0.00,
	"eyePlacex": -45.00,
    	"eyePlacey": -150.00,
	"caption": "You're a hole in 1!"
 },
 {
	"id": 4,
	"name": "Moon",
	 "category": "Anniversary",
	"image": "Love1",
	 "page2": "HA1",
	 "price": 4.00,
	"hairPlacex": 45.00,
    	"hairPlacey": 150.00,
	"eyePlacex": -45.00,
    	"eyePlacey": 150.00,
	"caption": "True Love know's no bounds"
 },
	{
	"id": 5,
	"name": "STOP",
	 "category": "Save the Date",
	"image": "Stop",
	 "price": 5.00,
	"hairPlacex": 0.00,
    	"hairPlacey": 0.00,
	"eyePlacex": 60,
    	"eyePlacey": 150.00,
	"caption": "STOP What you're doing!"
	
 },
	{
	"id": 6,
	"name": "BrideGroom1",
	 "category": "Save the Date",
	"image": "BrideGroom1",
	"page2": "HA1",
	 "price": 7.00,
	"hairPlacex": 0.00,
    	"hairPlacey": 0.00,
	"eyePlacex": -45.00,
    	"eyePlacey": -150.00,
	"caption": "Car you have a good BDAY!"
		
 },
	{
	"id": 7,
	"name": "Moon",
	"category": "Christmas",
	"image": "Love1",
	"page2": "HA1",
	"price": 4.00,
	"hairPlacex": 0.00,
    	"hairPlacey": 0.00,
	"eyePlacex": -45.00,
    	"eyePlacey": -150.00,
	"caption": "True Love know's no bounds"
		
 },
	{
	"id": 8,
	"name": "Golf 2",
	"category": "Birthday",
	"image": "Golf2",
	"page2": "HA1",
	"price": 4.00,
	"hairPlacex": 0.00,
    	"hairPlacey": 0.00,
	"eyePlacex": -45.00,
    	"eyePlacey": -150.00,
	"caption": "Fore!!"
 },
 {
	"id": 9,
	"name": "Car",
	 "category": "Birthday",
	"image": "BirthdayCard1",
	 "page2": "HA1",
	 "price": 4.00,
	 "hairPlacex": 0.00,
    	"hairPlacey": 0.00,
	"eyePlacex": -45.00,
    	"eyePlacey": -150.00,
	"caption": "Car you have a good BDAY!"
 },
	{
	"id": 10,
	"name": "Hippo",
	"category": "Birthday",
	"image": "BirthdayCard1",
	"page2": "HA1",
	"price": 4.00,
	"hairPlacex": 0.00,
    	"hairPlacey": 0.00,
	"eyePlacex": 45.00,
    	"eyePlacey": 150.00,
	"caption": "HIP HIP Hello"
 },
 {
	"id": 11,
	"name": "Car",
	"category": "Birthday",
	"image": "BirthdayCard1",
	"page2": "HA1",
	"price": 4.00,
	"hairPlacex": 0.00,
    	"hairPlacey": 0.00,
	"eyePlacex": -45.00,
    	"eyePlacey": 150.00,
	"caption": "Car you have a good BDAY!"
 }
]
